pypeta/__init__.py
pypeta/getstudyid.py
pypeta/gettoken.py
pypeta/hgvs_variant.py
pypeta/pypeta.py
pypeta/utils.py
pypeta-0.6.9.dist-info/LICENSE
pypeta-0.6.9.dist-info/METADATA
pypeta-0.6.9.dist-info/WHEEL
pypeta-0.6.9.dist-info/top_level.txt
pypeta-0.6.9.dist-info/RECORD
